sogouweixincrawl/SogouWeixinAccountListParser.py
sogouweixincrawl/SogouWeixinCrawl.py
sogouweixincrawl/SogouWeixinVerify.py
sogouweixincrawl/__init__.py
sogouweixincrawl/netcrawl/BaseCrawl.py
sogouweixincrawl/netcrawl/CreateCrawl.py
sogouweixincrawl/netcrawl/__init__.py
sogouweixincrawl-1.1.0.dist-info/LICENSE
sogouweixincrawl-1.1.0.dist-info/METADATA
sogouweixincrawl-1.1.0.dist-info/WHEEL
sogouweixincrawl-1.1.0.dist-info/top_level.txt
sogouweixincrawl-1.1.0.dist-info/RECORD
