Metadata-Version: 2.1
Name: sogouweixincrawl
Version: 1.1.0
Summary: sogouweixin crawl features
Home-page: https://github.com/Eilison/sogouweixinCrawl.git
Author: eilison
Author-email: 1277886419@qq.com
License: MIT License
Platform: all
Requires-Dist: lxml
Requires-Dist: pillow
Requires-Dist: netcrawl
Requires-Dist: selenium
